smol_dev/__init__.py
smol_dev/main.py
smol_dev/prompts.py
smol_dev/utils.py
smol_dev-0.0.4.dist-info/LICENSE
smol_dev-0.0.4.dist-info/METADATA
smol_dev-0.0.4.dist-info/WHEEL
smol_dev-0.0.4.dist-info/entry_points.txt
smol_dev-0.0.4.dist-info/RECORD
