Metadata-Version: 2.1
Name: smol-dev
Version: 0.0.4
Summary: python module of smol developer
License: MIT
Author: swyx
Author-email: swyx@dontemail.me
Requires-Python: >=3.11,<4.0
Classifier: License :: OSI Approved :: MIT License
Classifier: Programming Language :: Python :: 3
Classifier: Programming Language :: Python :: 3.11
Requires-Dist: openai (>=0.27.8,<0.28.0)
Requires-Dist: openai-function-call (>=0.0.5,<0.0.6)
Requires-Dist: tenacity (>=8.2.2,<9.0.0)
